CMakeLists.txt
LICENSE
LICENSE.md
MANIFEST.in
README.md
pyproject.toml
setup.py
version.txt
cmake/compiler_options.cmake
include/AccRQA_definitions.hpp
include/AccRQA_functions.hpp
include/AccRQA_library.hpp
include/AccRQA_printf.hpp
include/AccRQA_threads.hpp
include/AccRQA_utilities_comp_platform.hpp
include/AccRQA_utilities_distance.hpp
include/AccRQA_utilities_error.hpp
include/AccRQA_utilities_mem.hpp
src/AccRQA-GPU-HST.cu
src/AccRQA-GPU-RR.cu
src/AccRQA_CPU_function.cpp
src/AccRQA_CPU_function.hpp
src/AccRQA_GPU_function.hpp
src/AccRQA_R_bindings.cpp
src/AccRQA_functions.cpp
src/AccRQA_metrics.cuh
src/AccRQA_python_bindings.cpp
src/AccRQA_threads.cpp
src/AccRQA_utilities_mem.cpp
src/CMakeLists.txt
src/CMakeLists.txt:Zone.Identifier
src/GPU_reduction.cuh
src/GPU_reduction.cuh:Zone.Identifier
src/GPU_scan.cuh
src/GPU_timer.h
src/Makevars.in
src/accrqa/__init__.py
src/accrqa/accrqa.py
src/accrqa/accrqa_compplatform.py
src/accrqa/accrqa_distance.py
src/accrqa/accrqa_error.py
src/accrqa/accrqa_error.py:Zone.Identifier
src/accrqa/accrqa_lib.py
src/accrqa/accrqa_lib.py:Zone.Identifier
src/accrqa/accrqa_mem.py
src/accrqa/accrqa_mem.py:Zone.Identifier
src/accrqa/accrqa_test.py
src/accrqa.egg-info/PKG-INFO
src/accrqa.egg-info/SOURCES.txt
src/accrqa.egg-info/dependency_links.txt
src/accrqa.egg-info/requires.txt
src/accrqa.egg-info/top_level.txt