Metadata-Version: 2.4
Name: accrqa
Version: 1.0.1
Summary: AccRQA calculates recurrence quantification analysis (RQA)
Home-page: https://github.com/KAdamek/AccRQA
Author: Karel Adamek, Jan Novotny, Radim Panis, Marwan Norbert
License: MIT License
Project-URL: Documentation, https://kadamek.github.io/AccRQA/index.html
Project-URL: Repository, https://github.com/KAdamek/AccRQA.git
Project-URL: Issues, https://github.com/KAdamek/AccRQA/issues
Keywords: rqa,astronomy
Classifier: Development Status :: 5 - Production/Stable
Classifier: Environment :: Console
Classifier: Environment :: GPU :: NVIDIA CUDA :: 7.0
Classifier: Intended Audience :: Science/Research
Classifier: License :: OSI Approved :: MIT License
Classifier: Natural Language :: English
Classifier: Programming Language :: Python :: 3
Classifier: Topic :: Scientific/Engineering
Requires-Python: >=3.8
License-File: LICENSE
License-File: LICENSE.md
Requires-Dist: numpy>=1.7.0
Requires-Dist: pandas>=1.4.3
Provides-Extra: cuda
Requires-Dist: cupy-cuda12x>=12.0.0; extra == "cuda"
Dynamic: home-page
Dynamic: license-file
